sbd.py
dataset/industrial.py
etsc/etsc.py
segmentation/segmentation.py
seral/seral.py
seral-1.0.2.dist-info/METADATA
seral-1.0.2.dist-info/WHEEL
seral-1.0.2.dist-info/top_level.txt
seral-1.0.2.dist-info/RECORD
