Metadata-Version: 2.4
Name: seral
Version: 1.0.2
Summary: Implementation of Streaming ERAL algorithm (Stržinar et al., 2024)
Author-email: Žiga Stržinar <ziga.strzinar@ijs.si>
Project-URL: Homepage, https://repo.ijs.si/zstrzinar/streaming-eral
Classifier: Programming Language :: Python :: 3
Classifier: Operating System :: OS Independent
Requires-Python: >=3.11
Requires-Dist: numpy>=2.2.0
Requires-Dist: pandas>=2.2.0
Requires-Dist: scipy>=1.15.2
Requires-Dist: scikit-learn>=1.6.1
Requires-Dist: eral>=1.1.1
Requires-Dist: numba>=0.60.0
